LICENSE
MANIFEST.in
README
README.md
hmms.ipynb
requirements.txt
setup.cfg
setup.py
hmms/__init__.py
hmms/__main__.py
hmms/art.py
hmms/cthmm.c
hmms/cthmm.pyx
hmms/dthmm.c
hmms/dthmm.pyx
hmms/hmm.c
hmms/hmm.pxd
hmms/hmm.pyx
hmms/train.py
hmms.egg-info/PKG-INFO
hmms.egg-info/SOURCES.txt
hmms.egg-info/dependency_links.txt
hmms.egg-info/not-zip-safe
hmms.egg-info/requires.txt
hmms.egg-info/top_level.txt
test/common.py
test/experiments.py
test/test_cthmm.py
test/test_dthmm.py